{"version":1,"resource":"vscode-userdata:/home/zekiukas/.config/Code/User/settings.json","entries":[{"id":"Ux1p.json","timestamp":1670773147565},{"id":"r753.json","timestamp":1670773158054},{"id":"JKyA.json","timestamp":1670773237817},{"id":"WD9H.json","timestamp":1670773258710},{"id":"Pq7s.json","timestamp":1670773282415},{"id":"vXbr.json","timestamp":1670773307045},{"id":"yg4G.json","timestamp":1670773359883},{"id":"eNnM.json","timestamp":1670773450379},{"id":"L0Yf.json","timestamp":1670773473992},{"id":"5Bhb.json","timestamp":1670773636744},{"id":"qxyN.json","timestamp":1670876729716},{"id":"smu0.json","timestamp":1671292023111},{"id":"ZRcm.json","timestamp":1671304793904}]}